aesige/__init__.py
aesige/aes_arm.pyx
aesige/aes_arm_impl.c
aesige/aes_arm_impl.h
aesige/aes_ni.c
aesige/aes_ni.cp312-win_amd64.pyd
aesige/aes_ni.pyx
aesige/aes_ni_impl.c
aesige/aes_ni_impl.h
aesige-1.0.0.dist-info/licenses/LICENSE
aesige-1.0.0.dist-info/METADATA
aesige-1.0.0.dist-info/WHEEL
aesige-1.0.0.dist-info/top_level.txt
aesige-1.0.0.dist-info/RECORD
