Metadata-Version: 2.4
Name: aesige
Version: 1.0.0
Summary: Fast AES-256-IGE encryption with hardware acceleration (AES-NI/ARM CE)
Author: xGaDinc
License-Expression: Apache-2.0
Project-URL: Homepage, https://github.com/xGaDinc/aesige
Keywords: aes,ige,crypto,telegram,mtproto,aesni,arm
Classifier: Programming Language :: Python :: 3
Classifier: Programming Language :: Cython
Requires-Python: >=3.8
License-File: LICENSE
Dynamic: license-file
Dynamic: requires-python
